apptuit/__init__.py
apptuit/apptuit_client.py
apptuit/timeseries.py
apptuit/utils.py
apptuit/pyformance/__init__.py
apptuit/pyformance/apptuit_reporter.py
apptuit/pyformance/process_metrics.py
apptuit-2.4.2.data/data/LICENSE
apptuit-2.4.2.dist-info/LICENSE
apptuit-2.4.2.dist-info/METADATA
apptuit-2.4.2.dist-info/WHEEL
apptuit-2.4.2.dist-info/top_level.txt
apptuit-2.4.2.dist-info/RECORD
