Metadata-Version: 2.1
Name: apptuit
Version: 2.4.2
Summary: Apptuit Python Client
Home-page: https://github.com/ApptuitAI/apptuit-py
Author: Abhinav Upadhyay
Author-email: abhinav.updadhyay@agilitix.ai
License: Apache License 2.0
Platform: UNKNOWN
Classifier: Programming Language :: Python :: 2.7
Classifier: Programming Language :: Python :: 3.5
Classifier: Programming Language :: Python :: 3.6
Classifier: Programming Language :: Python :: 3.7
Classifier: Development Status :: 5 - Production/Stable
Classifier: Intended Audience :: Developers
Classifier: Operating System :: OS Independent
Classifier: Topic :: Software Development :: Libraries :: Python Modules
Requires-Dist: requests (>=2.13.0)
Requires-Dist: pyformance (>=0.4)
Requires-Dist: backports.functools-lru-cache (>=1.5) ; python_version < "3"
